pkgx/__init__.py
pkgx/cli.py
pkgx/managers.py
pkgx-0.1.1.dist-info/METADATA
pkgx-0.1.1.dist-info/WHEEL
pkgx-0.1.1.dist-info/entry_points.txt
pkgx-0.1.1.dist-info/top_level.txt
pkgx-0.1.1.dist-info/RECORD
