Metadata-Version: 2.4
Name: pkgx
Version: 0.1.1
Summary: Universal Package Manager - A wrapper for various system package managers
Author-email: pkgx Development <smurfjuggler@gmail.com>
License: MIT
Project-URL: home-page, https://github.com/udkyo/pkgx
Project-URL: repository, https://github.com/udkyo/pkgx
Project-URL: documentation, https://github.com/udkyo/pkgx#README.md
Keywords: package-manager,wrapper,cli,universal
Classifier: Development Status :: 4 - Beta
Classifier: Intended Audience :: Developers
Classifier: Intended Audience :: System Administrators
Classifier: License :: OSI Approved :: MIT License
Classifier: Operating System :: OS Independent
Classifier: Programming Language :: Python :: 3
Classifier: Programming Language :: Python :: 3.8
Classifier: Programming Language :: Python :: 3.9
Classifier: Programming Language :: Python :: 3.10
Classifier: Programming Language :: Python :: 3.11
Classifier: Programming Language :: Python :: 3.12
Classifier: Topic :: System :: Systems Administration
Classifier: Topic :: Utilities
Requires-Python: >=3.8
